core/__init__.py
core/constants.py
core/operators.py
core/sesolve.py
core/states.py
core/utils.py
signal/__init__.py
signal/transforms.py
vis/__init__.py
vis/utils.py
pytorch_quantum-0.3.dist-info/METADATA
pytorch_quantum-0.3.dist-info/WHEEL
pytorch_quantum-0.3.dist-info/top_level.txt
pytorch_quantum-0.3.dist-info/RECORD
