Metadata-Version: 2.1
Name: pytorch-quantum
Version: 0.3
Summary: Quantum Dynamics simulation with PyTorch
Author-email: Anurag Saha Roy <contact@anuragsaharoy.me>
Project-URL: Homepage, http://github.com/pytorch-quantum
Project-URL: Repository, http://github.com/pytorch-quantum/pytorch-quantum.git
Classifier: Development Status :: 3 - Alpha
Classifier: License :: OSI Approved :: Apache Software License
Classifier: Intended Audience :: Science/Research
Classifier: Operating System :: Unix
Classifier: Programming Language :: Python :: 3.10
Classifier: Topic :: Scientific/Engineering :: Artificial Intelligence
Classifier: Topic :: Scientific/Engineering :: Physics
Requires-Python: >=3.9
Requires-Dist: numpy
Requires-Dist: scipy
Requires-Dist: torch
Provides-Extra: dev
Requires-Dist: pytest ; extra == 'dev'
Provides-Extra: plotting
Requires-Dist: matplotlib ; extra == 'plotting'
